datasette_proxy_url/__init__.py
datasette_proxy_url-0.1.1.dist-info/LICENSE
datasette_proxy_url-0.1.1.dist-info/METADATA
datasette_proxy_url-0.1.1.dist-info/WHEEL
datasette_proxy_url-0.1.1.dist-info/entry_points.txt
datasette_proxy_url-0.1.1.dist-info/top_level.txt
datasette_proxy_url-0.1.1.dist-info/RECORD
