Metadata-Version: 2.1
Name: datasette-proxy-url
Version: 0.1.1
Summary: Proxy a URL through a Datasette instance
Author: Simon Willison
License: Apache-2.0
Project-URL: Homepage, https://github.com/datasette/datasette-proxy-url
Project-URL: Changelog, https://github.com/datasette/datasette-proxy-url/releases
Project-URL: Issues, https://github.com/datasette/datasette-proxy-url/issues
Project-URL: CI, https://github.com/datasette/datasette-proxy-url/actions
Classifier: Framework :: Datasette
Classifier: License :: OSI Approved :: Apache Software License
Requires-Python: >=3.8
License-File: LICENSE
Requires-Dist: datasette
Requires-Dist: httpx
Provides-Extra: test
Requires-Dist: pytest ; extra == 'test'
Requires-Dist: pytest-asyncio ; extra == 'test'
Requires-Dist: pytest-httpx ; extra == 'test'
Requires-Dist: datasette-test ; extra == 'test'
